torch_diode/__init__.py
torch_diode/__init___lib.py
torch_diode/model_registry.py
torch_diode/collection/__init__.py
torch_diode/collection/generic_data_utils.py
torch_diode/collection/matmul_data_utils.py
torch_diode/collection/matmul_dataset_collector.py
torch_diode/integration/__init__.py
torch_diode/integration/base_integration.py
torch_diode/integration/enhanced_inductor_choices.py
torch_diode/integration/inductor_integration.py
torch_diode/integration/kernel_conversions.py
torch_diode/integration/matmul_integration.py
torch_diode/model/__init__.py
torch_diode/model/directory_dataset_loader.py
torch_diode/model/matmul_dataset_loader.py
torch_diode/model/matmul_inference.py
torch_diode/model/matmul_model_config.py
torch_diode/model/matmul_model_trainer.py
torch_diode/model/matmul_model_v1.py
torch_diode/model/matmul_timing_model.py
torch_diode/model/model_utils.py
torch_diode/model/model_utils_common.py
torch_diode/model/model_wrapper.py
torch_diode/types/__init__.py
torch_diode/types/json_serializable.py
torch_diode/types/kernel_lut.py
torch_diode/types/matmul_dataset.py
torch_diode/types/matmul_types.py
torch_diode/utils/__init__.py
torch_diode/utils/dataset_utils.py
torch_diode/utils/debug_config.py
torch_diode/utils/feature_extraction.py
torch_diode/utils/visualization_utils.py
torch_diode_lib-0.1.1.dist-info/licenses/LICENSE
torch_diode_lib-0.1.1.dist-info/METADATA
torch_diode_lib-0.1.1.dist-info/WHEEL
torch_diode_lib-0.1.1.dist-info/top_level.txt
torch_diode_lib-0.1.1.dist-info/RECORD
