Metadata-Version: 2.4
Name: torch-diode-lib
Version: 0.1.1
Summary: A toolkit for matrix multiplication data collection, model training, and evaluation (library version without PyTorch Inductor auto-registration)
Author-email: Gabriel Ferns <gabeferns@meta.com>
License-Expression: MIT
Project-URL: Homepage, https://github.com/exclamaforte/diode
Project-URL: Repository, https://github.com/exclamaforte/diode.git
Project-URL: Documentation, https://exclamaforte.github.io/diode/
Project-URL: Bug Tracker, https://github.com/exclamaforte/diode/issues
Keywords: machine-learning,pytorch,torch,matrix-multiplication,heuristics,optimization,hardware,library
Classifier: Development Status :: 3 - Alpha
Classifier: Intended Audience :: Developers
Classifier: Intended Audience :: Science/Research
Classifier: Programming Language :: Python :: 3
Classifier: Programming Language :: Python :: 3.8
Classifier: Programming Language :: Python :: 3.9
Classifier: Programming Language :: Python :: 3.10
Classifier: Programming Language :: Python :: 3.11
Classifier: Programming Language :: Python :: 3.12
Classifier: Topic :: Scientific/Engineering :: Artificial Intelligence
Classifier: Topic :: Software Development :: Libraries :: Python Modules
Requires-Python: >=3.8
License-File: LICENSE
Requires-Dist: torch>=2.9.0.dev
Requires-Dist: msgpack>=1.0.0
Provides-Extra: lint
Requires-Dist: lintrunner>=0.12.0; extra == "lint"
Requires-Dist: matplotlib>=3.5.0; extra == "lint"
Requires-Dist: tqdm>=4.62.0; extra == "lint"
Requires-Dist: flake8==6.1.0; extra == "lint"
Requires-Dist: flake8-bugbear==23.3.23; extra == "lint"
Requires-Dist: flake8-comprehensions==3.15.0; extra == "lint"
Requires-Dist: flake8-executable==2.1.3; extra == "lint"
Requires-Dist: flake8-logging-format==0.9.0; extra == "lint"
Requires-Dist: flake8-pyi==23.3.1; extra == "lint"
Requires-Dist: flake8-simplify==0.19.3; extra == "lint"
Requires-Dist: mccabe==0.7.0; extra == "lint"
Requires-Dist: pycodestyle==2.11.1; extra == "lint"
Requires-Dist: pyflakes==3.1.0; extra == "lint"
Requires-Dist: mypy==1.16.0; extra == "lint"
Requires-Dist: types-requests==2.27.25; extra == "lint"
Requires-Dist: types-pyyaml==6.0.1; extra == "lint"
Requires-Dist: types-setuptools==79.0.0.20250422; extra == "lint"
Requires-Dist: ruff==0.12.2; extra == "lint"
Requires-Dist: black==23.12.1; extra == "lint"
Requires-Dist: usort==1.0.8.post1; extra == "lint"
Requires-Dist: isort==6.0.1; extra == "lint"
Requires-Dist: codespell[toml]==2.4.1; extra == "lint"
Requires-Dist: packaging==25.0; extra == "lint"
Requires-Dist: tomli==2.2.1; python_version < "3.11" and extra == "lint"
Dynamic: license-file
